{"beijing-guoan": [{"2024": {"sum": "473.046", "matches": "14", "average": "33.789"}}, {"2023": {"sum": "991.120", "matches": "30", "average": "33.037"}}, {"2021": {"sum": "18.492", "matches": "14", "average": "1.321"}}, {"2019": {"sum": "1.003.914", "matches": "30", "average": "33.464"}}, {"2018": {"sum": "1.007.680", "matches": "30", "average": "33.589"}}, {"2017": {"sum": "900.157", "matches": "30", "average": "30.005"}}, {"2016": {"sum": "939.111", "matches": "29", "average": "32.383"}}, {"2015": {"sum": "916.143", "matches": "28", "average": "32.719"}}, {"2014": {"sum": "924.880", "matches": "30", "average": "30.829"}}, {"2013": {"sum": "937.191", "matches": "30", "average": "31.240"}}, {"2012": {"sum": "889.453", "matches": "30", "average": "29.648"}}, {"2011": {"sum": "912.687", "matches": "30", "average": "30.423"}}, {"2010": {"sum": "578.588", "matches": "24", "average": "24.108"}}, {"2008": {"sum": "60.000", "matches": "3", "average": "20.000"}}], "chengdu-rongcheng": [{"2024": {"sum": "454.974", "matches": "14", "average": "32.498"}}, {"2023": {"sum": "809.009", "matches": "30", "average": "26.967"}}], "shandong-taishan": [{"2024": {"sum": "380.629", "matches": "14", "average": "27.188"}}, {"2023": {"sum": "739.491", "matches": "30", "average": "24.650"}}, {"2021": {"sum": "8.555", "matches": "14", "average": "611"}}, {"2019": {"sum": "749.131", "matches": "30", "average": "24.971"}}, {"2018": {"sum": "758.978", "matches": "30", "average": "25.299"}}, {"2017": {"sum": "836.161", "matches": "30", "average": "27.872"}}, {"2016": {"sum": "648.874", "matches": "30", "average": "21.629"}}, {"2015": {"sum": "611.121", "matches": "29", "average": "21.073"}}, {"2014": {"sum": "650.829", "matches": "30", "average": "21.694"}}, {"2013": {"sum": "715.390", "matches": "30", "average": "23.846"}}, {"2012": {"sum": "598.112", "matches": "30", "average": "19.937"}}, {"2011": {"sum": "478.316", "matches": "30", "average": "15.944"}}, {"2010": {"sum": "404.023", "matches": "24", "average": "16.834"}}, {"2008": {"sum": "76.000", "matches": "4", "average": "19.000"}}], "shanghai-shenhua": [{"2024": {"sum": "316.192", "matches": "14", "average": "22.585"}}, {"2023": {"sum": "713.110", "matches": "30", "average": "23.770"}}, {"2021": {"sum": "36.225", "matches": "14", "average": "2.588"}}, {"2019": {"sum": "682.239", "matches": "30", "average": "22.741"}}, {"2018": {"sum": "688.039", "matches": "30", "average": "22.935"}}, {"2017": {"sum": "676.282", "matches": "30", "average": "22.543"}}, {"2016": {"sum": "753.489", "matches": "30", "average": "25.116"}}, {"2015": {"sum": "648.040", "matches": "29", "average": "22.346"}}, {"2014": {"sum": "504.995", "matches": "30", "average": "16.833"}}, {"2013": {"sum": "512.655", "matches": "30", "average": "17.089"}}, {"2012": {"sum": "580.279", "matches": "30", "average": "19.343"}}, {"2011": {"sum": "430.440", "matches": "30", "average": "14.348"}}, {"2010": {"sum": "409.563", "matches": "26", "average": "15.752"}}, {"2008": {"sum": "37.000", "matches": "3", "average": "12.333"}}], "nantong-zhiyun": [{"2024": {"sum": "304.859", "matches": "14", "average": "21.776"}}, {"2023": {"sum": "543.528", "matches": "30", "average": "18.118"}}], "zhejiang-professional": [{"2024": {"sum": "304.040", "matches": "14", "average": "21.717"}}, {"2023": {"sum": "366.763", "matches": "30", "average": "12.225"}}, {"2016": {"sum": "522.837", "matches": "30", "average": "17.428"}}, {"2015": {"sum": "479.968", "matches": "29", "average": "16.551"}}, {"2014": {"sum": "453.223", "matches": "30", "average": "15.107"}}, {"2013": {"sum": "482.127", "matches": "30", "average": "16.071"}}, {"2012": {"sum": "386.150", "matches": "30", "average": "12.872"}}, {"2011": {"sum": "376.845", "matches": "30", "average": "12.562"}}, {"2010": {"sum": "405.547", "matches": "26", "average": "15.598"}}, {"2008": {"sum": "50.000", "matches": "4", "average": "12.500"}}], "shanghai-port-fc": [{"2024": {"sum": "281.947", "matches": "13", "average": "21.688"}}, {"2023": {"sum": "606.496", "matches": "30", "average": "20.217"}}, {"2021": {"sum": "26.885", "matches": "14", "average": "1.920"}}, {"2019": {"sum": "686.694", "matches": "30", "average": "22.890"}}, {"2018": {"sum": "716.620", "matches": "30", "average": "23.887"}}, {"2017": {"sum": "819.797", "matches": "30", "average": "27.327"}}, {"2016": {"sum": "811.031", "matches": "30", "average": "27.034"}}, {"2015": {"sum": "718.420", "matches": "29", "average": "24.773"}}, {"2014": {"sum": "476.038", "matches": "30", "average": "15.868"}}, {"2013": {"sum": "432.895", "matches": "30", "average": "14.430"}}], "henan-fc": [{"2024": {"sum": "239.389", "matches": "14", "average": "17.099"}}, {"2023": {"sum": "502.036", "matches": "30", "average": "16.735"}}, {"2021": {"sum": "5.699", "matches": "14", "average": "407"}}, {"2019": {"sum": "619.305", "matches": "30", "average": "20.644"}}, {"2018": {"sum": "641.237", "matches": "30", "average": "21.375"}}, {"2017": {"sum": "611.001", "matches": "30", "average": "20.367"}}, {"2016": {"sum": "641.441", "matches": "30", "average": "21.381"}}, {"2015": {"sum": "557.406", "matches": "29", "average": "19.221"}}, {"2014": {"sum": "530.610", "matches": "30", "average": "17.687"}}, {"2012": {"sum": "527.349", "matches": "30", "average": "17.578"}}, {"2011": {"sum": "501.913", "matches": "30", "average": "16.730"}}, {"2010": {"sum": "410.214", "matches": "26", "average": "15.777"}}, {"2008": {"sum": "50.000", "matches": "3", "average": "16.667"}}], "tianjin-jinmen-tiger": [{"2024": {"sum": "238.224", "matches": "14", "average": "17.016"}}, {"2023": {"sum": "739.432", "matches": "30", "average": "24.648"}}, {"2021": {"sum": "2.287", "matches": "14", "average": "163"}}, {"2019": {"sum": "608.889", "matches": "30", "average": "20.296"}}, {"2018": {"sum": "596.968", "matches": "30", "average": "19.899"}}, {"2017": {"sum": "582.917", "matches": "30", "average": "19.431"}}, {"2016": {"sum": "693.261", "matches": "30", "average": "23.109"}}, {"2015": {"sum": "557.693", "matches": "29", "average": "19.231"}}, {"2014": {"sum": "535.545", "matches": "30", "average": "17.852"}}, {"2013": {"sum": "509.610", "matches": "30", "average": "16.987"}}, {"2012": {"sum": "463.499", "matches": "30", "average": "15.450"}}, {"2011": {"sum": "561.461", "matches": "30", "average": "18.715"}}, {"2010": {"sum": "360.681", "matches": "25", "average": "14.427"}}, {"2008": {"sum": "37.000", "matches": "3", "average": "12.333"}}], "qingdao-hainiu": [{"2024": {"sum": "232.597", "matches": "14", "average": "16.614"}}, {"2023": {"sum": "559.006", "matches": "30", "average": "18.634"}}, {"2013": {"sum": "375.572", "matches": "30", "average": "12.519"}}, {"2012": {"sum": "411.646", "matches": "30", "average": "13.722"}}, {"2011": {"sum": "355.370", "matches": "30", "average": "11.846"}}, {"2010": {"sum": "278.005", "matches": "25", "average": "11.120"}}, {"2008": {"sum": "42.000", "matches": "3", "average": "14.000"}}], "qingdao-west-coast": [{"2024": {"sum": "228.366", "matches": "14", "average": "16.312"}}], "meizhou-hakka": [{"2024": {"sum": "206.363", "matches": "13", "average": "15.874"}}, {"2023": {"sum": "527.740", "matches": "30", "average": "17.591"}}], "shenzhen-peng-city": [{"2024": {"sum": "214.516", "matches": "14", "average": "15.323"}}], "wuhan-three-towns": [{"2024": {"sum": "199.830", "matches": "14", "average": "14.274"}}, {"2023": {"sum": "546.862", "matches": "30", "average": "18.229"}}], "changchun-yatai": [{"2024": {"sum": "193.022", "matches": "14", "average": "13.787"}}, {"2023": {"sum": "543.212", "matches": "30", "average": "18.107"}}, {"2021": {"sum": "5.193", "matches": "14", "average": "371"}}, {"2018": {"sum": "631.265", "matches": "30", "average": "21.042"}}, {"2017": {"sum": "562.095", "matches": "30", "average": "18.737"}}, {"2016": {"sum": "583.009", "matches": "30", "average": "19.434"}}, {"2015": {"sum": "473.839", "matches": "28", "average": "16.923"}}, {"2014": {"sum": "437.924", "matches": "30", "average": "14.597"}}, {"2013": {"sum": "421.486", "matches": "30", "average": "14.050"}}, {"2012": {"sum": "439.189", "matches": "30", "average": "14.640"}}, {"2011": {"sum": "474.867", "matches": "30", "average": "15.829"}}, {"2010": {"sum": "307.617", "matches": "25", "average": "12.305"}}, {"2008": {"sum": "25.000", "matches": "3", "average": "8.333"}}], "cangzhou-mighty-lions": [{"2024": {"sum": "171.002", "matches": "14", "average": "12.214"}}, {"2023": {"sum": "404.488", "matches": "30", "average": "13.483"}}, {"2021": {"sum": "7.151", "matches": "14", "average": "511"}}, {"2016": {"sum": "690.570", "matches": "30", "average": "23.019"}}, {"2015": {"sum": "675.913", "matches": "29", "average": "23.307"}}], "dalian-pro": [{"2023": {"sum": "561.880", "matches": "30", "average": "18.729"}}, {"2021": {"sum": "3.996", "matches": "14", "average": "285"}}, {"2019": {"sum": "796.441", "matches": "30", "average": "26.548"}}, {"2018": {"sum": "841.700", "matches": "30", "average": "28.057"}}, {"2014": {"sum": "427.750", "matches": "30", "average": "14.258"}}, {"2013": {"sum": "435.183", "matches": "30", "average": "14.506"}}, {"2012": {"sum": "511.273", "matches": "30", "average": "17.042"}}], "shenzhen-fc": [{"2023": {"sum": "384.909", "matches": "30", "average": "12.830"}}, {"2021": {"sum": "38.664", "matches": "14", "average": "2.762"}}, {"2019": {"sum": "565.592", "matches": "30", "average": "18.853"}}, {"2011": {"sum": "392.341", "matches": "30", "average": "13.078"}}, {"2010": {"sum": "346.946", "matches": "26", "average": "13.344"}}, {"2008": {"sum": "29.000", "matches": "3", "average": "9.667"}}], "guangzhou-fc": [{"2021": {"sum": "64.533", "matches": "14", "average": "4.610"}}, {"2019": {"sum": "1.111.748", "matches": "30", "average": "37.058"}}, {"2018": {"sum": "1.138.963", "matches": "30", "average": "37.965"}}, {"2017": {"sum": "1.136.357", "matches": "30", "average": "37.879"}}, {"2016": {"sum": "1.106.522", "matches": "30", "average": "36.884"}}, {"2015": {"sum": "1.055.086", "matches": "29", "average": "36.382"}}, {"2014": {"sum": "1.059.697", "matches": "30", "average": "35.323"}}, {"2013": {"sum": "1.041.831", "matches": "30", "average": "34.728"}}, {"2012": {"sum": "937.375", "matches": "30", "average": "31.246"}}, {"2011": {"sum": "1.016.098", "matches": "30", "average": "33.870"}}, {"2008": {"sum": "68.000", "matches": "4", "average": "17.000"}}], "guangzhou-city": [{"2021": {"sum": "38.294", "matches": "14", "average": "2.735"}}, {"2019": {"sum": "521.687", "matches": "30", "average": "17.390"}}, {"2018": {"sum": "490.610", "matches": "30", "average": "16.354"}}, {"2017": {"sum": "502.177", "matches": "30", "average": "16.739"}}, {"2016": {"sum": "504.885", "matches": "30", "average": "16.830"}}, {"2015": {"sum": "498.711", "matches": "29", "average": "17.197"}}, {"2014": {"sum": "430.701", "matches": "30", "average": "14.357"}}, {"2013": {"sum": "433.182", "matches": "30", "average": "14.439"}}, {"2012": {"sum": "392.312", "matches": "30", "average": "13.077"}}, {"2010": {"sum": "345.629", "matches": "26", "average": "13.293"}}, {"2008": {"sum": "30.000", "matches": "4", "average": "7.500"}}], "wuhan-yangtze-river": [{"2021": {"sum": "5.690", "matches": "14", "average": "406"}}, {"2019": {"sum": "629.565", "matches": "30", "average": "20.986"}}, {"2013": {"sum": "454.803", "matches": "30", "average": "15.160"}}], "qingdao-fc": [{"2021": {"sum": "5.070", "matches": "14", "average": "362"}}], "chongqing-liangjiang-athletic": [{"2021": {"sum": "3.792", "matches": "14", "average": "271"}}, {"2019": {"sum": "783.480", "matches": "30", "average": "26.116"}}, {"2018": {"sum": "793.386", "matches": "30", "average": "26.446"}}, {"2017": {"sum": "833.775", "matches": "30", "average": "27.793"}}, {"2016": {"sum": "827.220", "matches": "30", "average": "27.574"}}, {"2015": {"sum": "855.360", "matches": "29", "average": "29.495"}}, {"2010": {"sum": "315.407", "matches": "26", "average": "12.131"}}], "hebei-fc": [{"2021": {"sum": "1.710", "matches": "14", "average": "122"}}, {"2019": {"sum": "620.395", "matches": "30", "average": "20.680"}}, {"2018": {"sum": "584.210", "matches": "30", "average": "19.474"}}, {"2017": {"sum": "611.987", "matches": "30", "average": "20.400"}}, {"2016": {"sum": "634.580", "matches": "30", "average": "21.153"}}], "jiangsu-fc": [{"2019": {"sum": "776.433", "matches": "30", "average": "25.881"}}, {"2018": {"sum": "828.077", "matches": "30", "average": "27.603"}}, {"2017": {"sum": "816.106", "matches": "30", "average": "27.204"}}, {"2016": {"sum": "953.267", "matches": "30", "average": "31.776"}}, {"2015": {"sum": "706.777", "matches": "29", "average": "24.372"}}, {"2014": {"sum": "620.092", "matches": "30", "average": "20.670"}}, {"2013": {"sum": "683.570", "matches": "30", "average": "22.786"}}, {"2012": {"sum": "718.440", "matches": "30", "average": "23.948"}}, {"2011": {"sum": "517.630", "matches": "30", "average": "17.254"}}, {"2010": {"sum": "327.924", "matches": "27", "average": "12.145"}}], "tianjin-tianhai": [{"2019": {"sum": "580.617", "matches": "30", "average": "19.354"}}, {"2018": {"sum": "657.292", "matches": "30", "average": "21.910"}}, {"2017": {"sum": "758.002", "matches": "30", "average": "25.267"}}], "beijing-renhe-fc": [{"2019": {"sum": "416.288", "matches": "30", "average": "13.876"}}, {"2018": {"sum": "551.175", "matches": "30", "average": "18.373"}}, {"2015": {"sum": "499.730", "matches": "29", "average": "17.232"}}, {"2014": {"sum": "470.798", "matches": "30", "average": "15.693"}}, {"2013": {"sum": "560.805", "matches": "30", "average": "18.694"}}, {"2012": {"sum": "690.906", "matches": "30", "average": "23.030"}}, {"2011": {"sum": "681.310", "matches": "30", "average": "22.710"}}, {"2010": {"sum": "590.329", "matches": "27", "average": "21.864"}}, {"2008": {"sum": "67.000", "matches": "4", "average": "16.750"}}], "guizhou-fc": [{"2018": {"sum": "586.508", "matches": "30", "average": "19.550"}}, {"2017": {"sum": "656.581", "matches": "30", "average": "21.886"}}], "yanbian-fc": [{"2017": {"sum": "612.182", "matches": "30", "average": "20.406"}}, {"2016": {"sum": "674.246", "matches": "30", "average": "22.475"}}], "liaoning-hongyn": [{"2017": {"sum": "492.237", "matches": "30", "average": "16.408"}}, {"2016": {"sum": "601.191", "matches": "29", "average": "20.731"}}, {"2015": {"sum": "465.349", "matches": "29", "average": "16.047"}}, {"2014": {"sum": "449.560", "matches": "30", "average": "14.985"}}, {"2013": {"sum": "543.697", "matches": "30", "average": "18.123"}}, {"2012": {"sum": "530.281", "matches": "30", "average": "17.676"}}, {"2011": {"sum": "541.174", "matches": "30", "average": "18.039"}}, {"2010": {"sum": "298.846", "matches": "25", "average": "11.954"}}, {"2008": {"sum": "89.000", "matches": "4", "average": "22.250"}}], "shanghai-shenxin": [{"2015": {"sum": "394.644", "matches": "29", "average": "13.608"}}, {"2014": {"sum": "398.794", "matches": "30", "average": "13.293"}}, {"2013": {"sum": "374.275", "matches": "30", "average": "12.476"}}, {"2012": {"sum": "432.238", "matches": "30", "average": "14.408"}}, {"2011": {"sum": "382.016", "matches": "30", "average": "12.734"}}, {"2010": {"sum": "340.535", "matches": "25", "average": "13.621"}}], "shaoxing-keqiao-yueji": [{"2014": {"sum": "631.624", "matches": "30", "average": "21.054"}}], "dalian-shide": [{"2012": {"sum": "449.130", "matches": "30", "average": "14.971"}}, {"2011": {"sum": "500.039", "matches": "30", "average": "16.668"}}, {"2010": {"sum": "384.896", "matches": "27", "average": "14.255"}}, {"2008": {"sum": "62.000", "matches": "4", "average": "15.500"}}], "chengdu-blades": [{"2011": {"sum": "361.547", "matches": "30", "average": "12.052"}}, {"2008": {"sum": "93.000", "matches": "4", "average": "23.250"}}], "wuhan-guanggu": [{"2008": {"sum": "39.000", "matches": "3", "average": "13.000"}}]}