{"fc-zlin-a-junioren": [{"2023/2024": {"sum": "3.291", "matches": "30", "average": "110"}}, {"2022/2023": {"sum": "2.531", "matches": "30", "average": "84"}}], "fc-zbrojovka-brno-a-junioren": [{"2023/2024": {"sum": "3.227", "matches": "30", "average": "108"}}, {"2022/2023": {"sum": "2.170", "matches": "30", "average": "72"}}], "ac-sparta-praha-a-junioren": [{"2023/2024": {"sum": "3.174", "matches": "30", "average": "106"}}, {"2022/2023": {"sum": "4.133", "matches": "30", "average": "138"}}], "slavia-praha-a-junioren": [{"2023/2024": {"sum": "2.997", "matches": "30", "average": "100"}}, {"2022/2023": {"sum": "3.141", "matches": "30", "average": "105"}}], "vysocina-jihlava-a-junioren": [{"2023/2024": {"sum": "2.943", "matches": "30", "average": "98"}}, {"2022/2023": {"sum": "3.209", "matches": "30", "average": "107"}}], "1-fc-slovacko-a-junioren": [{"2023/2024": {"sum": "2.922", "matches": "30", "average": "97"}}, {"2022/2023": {"sum": "2.923", "matches": "30", "average": "97"}}], "banik-ostrava-a-junioren": [{"2023/2024": {"sum": "2.879", "matches": "30", "average": "96"}}, {"2022/2023": {"sum": "2.627", "matches": "30", "average": "88"}}], "dynamo-ceske-budejovice-a-junioren": [{"2023/2024": {"sum": "2.841", "matches": "30", "average": "95"}}, {"2022/2023": {"sum": "2.312", "matches": "30", "average": "77"}}], "sigma-olomouc-a-junioren": [{"2023/2024": {"sum": "2.795", "matches": "30", "average": "93"}}, {"2022/2023": {"sum": "2.461", "matches": "30", "average": "82"}}], "mfk-karvina-a-junioren": [{"2023/2024": {"sum": "2.769", "matches": "30", "average": "92"}}, {"2022/2023": {"sum": "2.242", "matches": "30", "average": "75"}}], "fk-dukla-praha-a-junioren": [{"2023/2024": {"sum": "2.650", "matches": "30", "average": "88"}}, {"2022/2023": {"sum": "2.526", "matches": "30", "average": "84"}}], "fk-pardubice-a-junioren": [{"2023/2024": {"sum": "2.555", "matches": "30", "average": "85"}}, {"2022/2023": {"sum": "2.316", "matches": "30", "average": "77"}}], "fk-frydek-mistek-a-junioren": [{"2023/2024": {"sum": "2.547", "matches": "30", "average": "85"}}], "viktoria-plzen-a-junioren": [{"2023/2024": {"sum": "2.437", "matches": "30", "average": "81"}}, {"2022/2023": {"sum": "2.252", "matches": "30", "average": "75"}}], "slovan-liberec-a-junioren": [{"2023/2024": {"sum": "2.397", "matches": "30", "average": "80"}}], "fk-mlada-boleslav-a-junioren": [{"2023/2024": {"sum": "2.406", "matches": "30", "average": "80"}}, {"2022/2023": {"sum": "2.353", "matches": "30", "average": "78"}}], "fc-hradec-kralove-a-junioren": [{"2022/2023": {"sum": "2.517", "matches": "30", "average": "84"}}], "fk-viagem-pribram-a-junioren": [{"2022/2023": {"sum": "1.853", "matches": "30", "average": "62"}}]}