{"hamburger-sv": [{"1962/1963": {"sum": "496.400", "matches": "30", "average": "16.547"}}, {"1961/1962": {"sum": "408.000", "matches": "30", "average": "13.600"}}, {"1960/1961": {"sum": "409.000", "matches": "29", "average": "14.103"}}, {"1959/1960": {"sum": "431.010", "matches": "29", "average": "14.862"}}, {"1958/1959": {"sum": "481.000", "matches": "30", "average": "16.033"}}, {"1957/1958": {"sum": "451.000", "matches": "30", "average": "15.033"}}, {"1956/1957": {"sum": "507.000", "matches": "30", "average": "16.900"}}, {"1955/1956": {"sum": "469.000", "matches": "30", "average": "15.633"}}, {"1954/1955": {"sum": "538.000", "matches": "30", "average": "17.933"}}, {"1953/1954": {"sum": "348.000", "matches": "30", "average": "11.600"}}, {"1952/1953": {"sum": "415.000", "matches": "30", "average": "13.833"}}, {"1951/1952": {"sum": "408.000", "matches": "30", "average": "13.600"}}, {"1950/1951": {"sum": "380.200", "matches": "25", "average": "15.208"}}], "werder-bremen": [{"1962/1963": {"sum": "405.500", "matches": "30", "average": "13.517"}}, {"1961/1962": {"sum": "277.000", "matches": "30", "average": "9.233"}}, {"1960/1961": {"sum": "301.000", "matches": "30", "average": "10.033"}}, {"1959/1960": {"sum": "312.500", "matches": "30", "average": "10.417"}}, {"1958/1959": {"sum": "298.500", "matches": "30", "average": "9.950"}}, {"1957/1958": {"sum": "228.000", "matches": "30", "average": "7.600"}}, {"1956/1957": {"sum": "211.000", "matches": "30", "average": "7.033"}}, {"1955/1956": {"sum": "262.000", "matches": "30", "average": "8.733"}}, {"1954/1955": {"sum": "302.000", "matches": "30", "average": "10.067"}}, {"1953/1954": {"sum": "302.500", "matches": "30", "average": "10.083"}}, {"1952/1953": {"sum": "344.000", "matches": "30", "average": "11.467"}}, {"1951/1952": {"sum": "311.000", "matches": "30", "average": "10.367"}}, {"1950/1951": {"sum": "337.000", "matches": "25", "average": "13.480"}}], "arminia-hannover": [{"1962/1963": {"sum": "380.000", "matches": "30", "average": "12.667"}}, {"1956/1957": {"sum": "236.000", "matches": "30", "average": "7.867"}}, {"1955/1956": {"sum": "233.500", "matches": "30", "average": "7.783"}}, {"1954/1955": {"sum": "232.500", "matches": "30", "average": "7.750"}}, {"1953/1954": {"sum": "234.500", "matches": "30", "average": "7.817"}}, {"1952/1953": {"sum": "204.000", "matches": "30", "average": "6.800"}}, {"1951/1952": {"sum": "218.500", "matches": "30", "average": "7.283"}}, {"1950/1951": {"sum": "183.200", "matches": "26", "average": "7.046"}}], "hannover-96": [{"1962/1963": {"sum": "262.800", "matches": "30", "average": "8.760"}}, {"1961/1962": {"sum": "184.500", "matches": "30", "average": "6.150"}}, {"1960/1961": {"sum": "299.000", "matches": "29", "average": "10.310"}}, {"1959/1960": {"sum": "317.000", "matches": "30", "average": "10.567"}}, {"1958/1959": {"sum": "258.000", "matches": "30", "average": "8.600"}}, {"1957/1958": {"sum": "282.200", "matches": "29", "average": "9.731"}}, {"1956/1957": {"sum": "397.000", "matches": "30", "average": "13.233"}}, {"1955/1956": {"sum": "358.000", "matches": "30", "average": "11.933"}}, {"1954/1955": {"sum": "362.000", "matches": "30", "average": "12.067"}}, {"1953/1954": {"sum": "438.000", "matches": "30", "average": "14.600"}}, {"1952/1953": {"sum": "209.500", "matches": "30", "average": "6.983"}}, {"1951/1952": {"sum": "209.500", "matches": "30", "average": "6.983"}}, {"1950/1951": {"sum": "193.500", "matches": "25", "average": "7.740"}}], "eintracht-braunschweig": [{"1962/1963": {"sum": "256.793", "matches": "30", "average": "8.560"}}, {"1961/1962": {"sum": "234.000", "matches": "30", "average": "7.800"}}, {"1960/1961": {"sum": "168.000", "matches": "30", "average": "5.600"}}, {"1959/1960": {"sum": "268.000", "matches": "29", "average": "9.241"}}, {"1958/1959": {"sum": "270.500", "matches": "30", "average": "9.017"}}, {"1957/1958": {"sum": "301.500", "matches": "30", "average": "10.050"}}, {"1956/1957": {"sum": "277.400", "matches": "30", "average": "9.247"}}, {"1955/1956": {"sum": "273.500", "matches": "30", "average": "9.117"}}, {"1954/1955": {"sum": "328.000", "matches": "30", "average": "10.933"}}, {"1953/1954": {"sum": "350.500", "matches": "30", "average": "11.683"}}, {"1951/1952": {"sum": "250.300", "matches": "30", "average": "8.343"}}, {"1950/1951": {"sum": "218.200", "matches": "25", "average": "8.728"}}], "vfl-osnabrueck": [{"1962/1963": {"sum": "214.100", "matches": "30", "average": "7.137"}}, {"1961/1962": {"sum": "144.500", "matches": "30", "average": "4.817"}}, {"1960/1961": {"sum": "163.400", "matches": "29", "average": "5.634"}}, {"1959/1960": {"sum": "210.500", "matches": "30", "average": "7.017"}}, {"1958/1959": {"sum": "210.000", "matches": "30", "average": "7.000"}}, {"1957/1958": {"sum": "212.000", "matches": "30", "average": "7.067"}}, {"1956/1957": {"sum": "204.000", "matches": "30", "average": "6.800"}}, {"1955/1956": {"sum": "215.000", "matches": "30", "average": "7.167"}}, {"1954/1955": {"sum": "208.000", "matches": "30", "average": "6.933"}}, {"1953/1954": {"sum": "254.500", "matches": "30", "average": "8.483"}}, {"1952/1953": {"sum": "305.500", "matches": "30", "average": "10.183"}}, {"1951/1952": {"sum": "317.000", "matches": "30", "average": "10.567"}}, {"1950/1951": {"sum": "258.200", "matches": "25", "average": "10.328"}}], "holstein-kiel": [{"1962/1963": {"sum": "208.200", "matches": "30", "average": "6.940"}}, {"1961/1962": {"sum": "187.700", "matches": "30", "average": "6.257"}}, {"1960/1961": {"sum": "161.100", "matches": "30", "average": "5.370"}}, {"1959/1960": {"sum": "190.500", "matches": "28", "average": "6.804"}}, {"1958/1959": {"sum": "216.000", "matches": "30", "average": "7.200"}}, {"1957/1958": {"sum": "224.500", "matches": "30", "average": "7.483"}}, {"1956/1957": {"sum": "288.500", "matches": "30", "average": "9.617"}}, {"1955/1956": {"sum": "257.000", "matches": "30", "average": "8.567"}}, {"1954/1955": {"sum": "206.000", "matches": "30", "average": "6.867"}}, {"1953/1954": {"sum": "211.500", "matches": "30", "average": "7.050"}}, {"1952/1953": {"sum": "337.500", "matches": "30", "average": "11.250"}}, {"1951/1952": {"sum": "284.000", "matches": "30", "average": "9.467"}}, {"1950/1951": {"sum": "205.200", "matches": "25", "average": "8.208"}}], "fc-st-pauli": [{"1962/1963": {"sum": "196.000", "matches": "30", "average": "6.533"}}, {"1961/1962": {"sum": "190.850", "matches": "30", "average": "6.362"}}, {"1960/1961": {"sum": "224.700", "matches": "30", "average": "7.490"}}, {"1959/1960": {"sum": "290.000", "matches": "30", "average": "9.667"}}, {"1958/1959": {"sum": "212.500", "matches": "30", "average": "7.083"}}, {"1957/1958": {"sum": "199.500", "matches": "30", "average": "6.650"}}, {"1956/1957": {"sum": "224.000", "matches": "30", "average": "7.467"}}, {"1955/1956": {"sum": "204.500", "matches": "30", "average": "6.817"}}, {"1954/1955": {"sum": "243.500", "matches": "30", "average": "8.117"}}, {"1953/1954": {"sum": "271.900", "matches": "30", "average": "9.063"}}, {"1952/1953": {"sum": "245.500", "matches": "30", "average": "8.183"}}, {"1951/1952": {"sum": "291.000", "matches": "30", "average": "9.700"}}, {"1950/1951": {"sum": "293.000", "matches": "25", "average": "11.720"}}], "vfb-oldenburg": [{"1962/1963": {"sum": "185.100", "matches": "30", "average": "6.170"}}, {"1961/1962": {"sum": "203.600", "matches": "30", "average": "6.787"}}, {"1960/1961": {"sum": "262.500", "matches": "30", "average": "8.750"}}, {"1955/1956": {"sum": "205.500", "matches": "30", "average": "6.850"}}, {"1954/1955": {"sum": "236.000", "matches": "30", "average": "7.867"}}, {"1950/1951": {"sum": "221.500", "matches": "25", "average": "8.860"}}], "vfv-hildesheim": [{"1962/1963": {"sum": "173.500", "matches": "30", "average": "5.783"}}, {"1961/1962": {"sum": "250.500", "matches": "30", "average": "8.350"}}, {"1960/1961": {"sum": "195.000", "matches": "30", "average": "6.500"}}, {"1959/1960": {"sum": "199.700", "matches": "28", "average": "7.132"}}, {"1958/1959": {"sum": "233.500", "matches": "30", "average": "7.783"}}], "vfb-luebeck": [{"1962/1963": {"sum": "165.400", "matches": "30", "average": "5.513"}}, {"1960/1961": {"sum": "182.000", "matches": "30", "average": "6.067"}}, {"1959/1960": {"sum": "259.000", "matches": "30", "average": "8.633"}}, {"1957/1958": {"sum": "244.200", "matches": "30", "average": "8.140"}}, {"1953/1954": {"sum": "231.000", "matches": "30", "average": "7.700"}}, {"1952/1953": {"sum": "260.000", "matches": "30", "average": "8.667"}}], "tus-bremerhaven-93": [{"1962/1963": {"sum": "148.000", "matches": "30", "average": "4.933"}}, {"1961/1962": {"sum": "154.500", "matches": "30", "average": "5.150"}}, {"1960/1961": {"sum": "134.500", "matches": "30", "average": "4.483"}}, {"1959/1960": {"sum": "222.700", "matches": "30", "average": "7.423"}}, {"1958/1959": {"sum": "191.500", "matches": "30", "average": "6.383"}}, {"1957/1958": {"sum": "195.300", "matches": "30", "average": "6.510"}}, {"1956/1957": {"sum": "225.500", "matches": "30", "average": "7.517"}}, {"1955/1956": {"sum": "183.500", "matches": "30", "average": "6.117"}}, {"1954/1955": {"sum": "272.000", "matches": "30", "average": "9.067"}}, {"1953/1954": {"sum": "188.500", "matches": "30", "average": "6.283"}}, {"1952/1953": {"sum": "196.500", "matches": "30", "average": "6.550"}}, {"1951/1952": {"sum": "218.500", "matches": "30", "average": "7.283"}}, {"1950/1951": {"sum": "199.000", "matches": "24", "average": "8.292"}}], "vfr-neumuenster": [{"1962/1963": {"sum": "136.700", "matches": "30", "average": "4.557"}}, {"1961/1962": {"sum": "158.400", "matches": "30", "average": "5.280"}}, {"1960/1961": {"sum": "146.800", "matches": "30", "average": "4.893"}}, {"1959/1960": {"sum": "150.700", "matches": "30", "average": "5.023"}}, {"1958/1959": {"sum": "180.500", "matches": "30", "average": "6.017"}}, {"1957/1958": {"sum": "162.000", "matches": "30", "average": "5.400"}}, {"1956/1957": {"sum": "189.500", "matches": "30", "average": "6.317"}}, {"1955/1956": {"sum": "225.500", "matches": "30", "average": "7.517"}}], "altona-93": [{"1962/1963": {"sum": "129.293", "matches": "30", "average": "4.310"}}, {"1961/1962": {"sum": "135.800", "matches": "30", "average": "4.527"}}, {"1960/1961": {"sum": "170.200", "matches": "30", "average": "5.673"}}, {"1959/1960": {"sum": "169.000", "matches": "30", "average": "5.633"}}, {"1958/1959": {"sum": "226.500", "matches": "30", "average": "7.550"}}, {"1957/1958": {"sum": "200.700", "matches": "30", "average": "6.690"}}, {"1956/1957": {"sum": "203.000", "matches": "30", "average": "6.767"}}, {"1955/1956": {"sum": "192.500", "matches": "30", "average": "6.417"}}, {"1954/1955": {"sum": "238.000", "matches": "30", "average": "7.933"}}, {"1953/1954": {"sum": "240.400", "matches": "30", "average": "8.013"}}, {"1952/1953": {"sum": "320.000", "matches": "30", "average": "10.667"}}, {"1950/1951": {"sum": "159.000", "matches": "25", "average": "6.360"}}], "fc-bergedorf-85": [{"1962/1963": {"sum": "128.500", "matches": "30", "average": "4.283"}}, {"1961/1962": {"sum": "179.500", "matches": "30", "average": "5.983"}}, {"1960/1961": {"sum": "163.000", "matches": "30", "average": "5.433"}}, {"1959/1960": {"sum": "195.500", "matches": "29", "average": "6.741"}}, {"1958/1959": {"sum": "267.200", "matches": "30", "average": "8.907"}}], "wtsv-concordia": [{"1962/1963": {"sum": "123.900", "matches": "30", "average": "4.130"}}, {"1961/1962": {"sum": "126.200", "matches": "30", "average": "4.207"}}, {"1960/1961": {"sum": "140.500", "matches": "29", "average": "4.845"}}, {"1959/1960": {"sum": "176.200", "matches": "30", "average": "5.873"}}, {"1958/1959": {"sum": "190.500", "matches": "30", "average": "6.350"}}, {"1957/1958": {"sum": "177.300", "matches": "29", "average": "6.114"}}, {"1956/1957": {"sum": "208.000", "matches": "30", "average": "6.933"}}, {"1952/1953": {"sum": "178.000", "matches": "30", "average": "5.933"}}, {"1951/1952": {"sum": "160.500", "matches": "30", "average": "5.350"}}, {"1950/1951": {"sum": "146.000", "matches": "26", "average": "5.615"}}], "bremer-sv": [{"1961/1962": {"sum": "138.500", "matches": "30", "average": "4.617"}}, {"1954/1955": {"sum": "185.000", "matches": "30", "average": "6.167"}}, {"1953/1954": {"sum": "185.000", "matches": "30", "average": "6.167"}}, {"1952/1953": {"sum": "199.500", "matches": "30", "average": "6.650"}}, {"1951/1952": {"sum": "247.500", "matches": "30", "average": "8.250"}}, {"1950/1951": {"sum": "181.000", "matches": "25", "average": "7.240"}}], "eintracht-nordhorn": [{"1961/1962": {"sum": "122.350", "matches": "30", "average": "4.078"}}, {"1958/1959": {"sum": "149.200", "matches": "30", "average": "4.973"}}, {"1957/1958": {"sum": "135.100", "matches": "30", "average": "4.503"}}, {"1956/1957": {"sum": "160.000", "matches": "30", "average": "5.333"}}, {"1955/1956": {"sum": "212.000", "matches": "30", "average": "7.067"}}], "heider-sv": [{"1960/1961": {"sum": "132.500", "matches": "30", "average": "4.417"}}, {"1956/1957": {"sum": "164.500", "matches": "30", "average": "5.483"}}], "1-fc-phoenix-luebeck": [{"1959/1960": {"sum": "189.200", "matches": "29", "average": "6.524"}}, {"1958/1959": {"sum": "202.000", "matches": "30", "average": "6.733"}}, {"1957/1958": {"sum": "216.000", "matches": "30", "average": "7.200"}}], "eintracht-osnabrueck": [{"1959/1960": {"sum": "132.110", "matches": "30", "average": "4.404"}}, {"1952/1953": {"sum": "165.000", "matches": "30", "average": "5.500"}}, {"1951/1952": {"sum": "171.000", "matches": "30", "average": "5.700"}}, {"1950/1951": {"sum": "191.000", "matches": "26", "average": "7.346"}}], "vfl-wolfsburg": [{"1958/1959": {"sum": "166.000", "matches": "30", "average": "5.533"}}, {"1957/1958": {"sum": "177.500", "matches": "30", "average": "5.917"}}, {"1956/1957": {"sum": "175.000", "matches": "30", "average": "5.833"}}, {"1955/1956": {"sum": "175.500", "matches": "30", "average": "5.850"}}, {"1954/1955": {"sum": "212.500", "matches": "30", "average": "7.083"}}], "1-sc-goettingen-05": [{"1957/1958": {"sum": "140.200", "matches": "30", "average": "4.673"}}, {"1956/1957": {"sum": "194.400", "matches": "30", "average": "6.480"}}, {"1955/1956": {"sum": "191.500", "matches": "30", "average": "6.383"}}, {"1954/1955": {"sum": "190.000", "matches": "30", "average": "6.333"}}, {"1953/1954": {"sum": "238.500", "matches": "30", "average": "7.950"}}, {"1952/1953": {"sum": "230.000", "matches": "30", "average": "7.667"}}, {"1951/1952": {"sum": "220.500", "matches": "30", "average": "7.350"}}, {"1950/1951": {"sum": "230.000", "matches": "25", "average": "9.200"}}], "eimsbuetteler-tv": [{"1955/1956": {"sum": "140.500", "matches": "30", "average": "4.683"}}, {"1954/1955": {"sum": "189.000", "matches": "30", "average": "6.300"}}, {"1953/1954": {"sum": "201.000", "matches": "30", "average": "6.700"}}, {"1952/1953": {"sum": "205.000", "matches": "30", "average": "6.833"}}, {"1951/1952": {"sum": "161.300", "matches": "30", "average": "5.377"}}, {"1950/1951": {"sum": "145.200", "matches": "25", "average": "5.808"}}], "harburger-tb": [{"1954/1955": {"sum": "165.500", "matches": "30", "average": "5.517"}}, {"1953/1954": {"sum": "186.000", "matches": "30", "average": "6.200"}}, {"1952/1953": {"sum": "175.000", "matches": "30", "average": "5.833"}}], "victoria-hamburg": [{"1953/1954": {"sum": "164.000", "matches": "30", "average": "5.467"}}, {"1951/1952": {"sum": "137.000", "matches": "30", "average": "4.567"}}], "lueneburger-sk": [{"1951/1952": {"sum": "142.000", "matches": "30", "average": "4.733"}}], "itzehoer-sv-09": [{"1950/1951": {"sum": "116.000", "matches": "24", "average": "4.833"}}]}