{"sporting-braga": [{"2023/2024": {"sum": "56.018", "matches": "1", "average": "56.018"}}, {"2022/2023": {"sum": "12.491", "matches": "1", "average": "12.491"}}, {"2018/2019": {"sum": "46.672", "matches": "4", "average": "11.668"}}, {"2016/2017": {"sum": "4.202", "matches": "2", "average": "2.101"}}, {"2015/2016": {"sum": "15.537", "matches": "2", "average": "7.769"}}, {"2014/2015": {"sum": "75.575", "matches": "4", "average": "18.894"}}, {"2013/2014": {"sum": "11.100", "matches": "3", "average": "3.700"}}, {"2012/2013": {"sum": "7.870", "matches": "1", "average": "7.870"}}], "fc-famalicao": [{"2023/2024": {"sum": "52.609", "matches": "1", "average": "52.609"}}, {"2019/2020": {"sum": "47.157", "matches": "3", "average": "15.719"}}, {"2016/2017": {"sum": "3.109", "matches": "1", "average": "3.109"}}, {"2014/2015": {"sum": "13.183", "matches": "2", "average": "6.592"}}, {"2013/2014": {"sum": "3.000", "matches": "1", "average": "3.000"}}], "cd-santa-clara": [{"2023/2024": {"sum": "45.393", "matches": "1", "average": "45.393"}}, {"2019/2020": {"sum": "890", "matches": "1", "average": "890"}}, {"2018/2019": {"sum": "2.217", "matches": "1", "average": "2.217"}}], "sl-benfica": [{"2023/2024": {"sum": "216.931", "matches": "5", "average": "43.386"}}, {"2022/2023": {"sum": "12.491", "matches": "1", "average": "12.491"}}, {"2019/2020": {"sum": "75.275", "matches": "3", "average": "25.092"}}, {"2018/2019": {"sum": "134.655", "matches": "6", "average": "22.443"}}, {"2016/2017": {"sum": "58.865", "matches": "4", "average": "14.716"}}, {"2015/2016": {"sum": "41.244", "matches": "1", "average": "41.244"}}, {"2014/2015": {"sum": "57.771", "matches": "3", "average": "19.257"}}, {"2013/2014": {"sum": "184.689", "matches": "6", "average": "30.782"}}, {"2012/2013": {"sum": "53.968", "matches": "2", "average": "26.984"}}, {"2007/2008": {"sum": "37.204", "matches": "1", "average": "37.204"}}], "sporting-cp": [{"2023/2024": {"sum": "144.640", "matches": "5", "average": "28.928"}}, {"2021/2022": {"sum": "91.640", "matches": "2", "average": "45.820"}}, {"2018/2019": {"sum": "113.145", "matches": "5", "average": "22.629"}}, {"2017/2018": {"sum": "79.155", "matches": "3", "average": "26.385"}}, {"2016/2017": {"sum": "13.422", "matches": "3", "average": "4.474"}}, {"2015/2016": {"sum": "44.076", "matches": "2", "average": "22.038"}}, {"2014/2015": {"sum": "112.257", "matches": "7", "average": "16.037"}}, {"2013/2014": {"sum": "47.156", "matches": "1", "average": "47.156"}}, {"2011/2012": {"sum": "21.522", "matches": "1", "average": "21.522"}}, {"2009/2010": {"sum": "20.146", "matches": "2", "average": "10.073"}}, {"2007/2008": {"sum": "37.204", "matches": "1", "average": "37.204"}}], "fc-porto": [{"2023/2024": {"sum": "98.141", "matches": "4", "average": "24.535"}}, {"2022/2023": {"sum": "6.685", "matches": "1", "average": "6.685"}}, {"2021/2022": {"sum": "91.640", "matches": "2", "average": "45.820"}}, {"2019/2020": {"sum": "39.151", "matches": "3", "average": "13.050"}}, {"2018/2019": {"sum": "65.195", "matches": "4", "average": "16.299"}}, {"2017/2018": {"sum": "79.809", "matches": "3", "average": "26.603"}}, {"2016/2017": {"sum": "8.000", "matches": "1", "average": "8.000"}}, {"2015/2016": {"sum": "8.955", "matches": "2", "average": "4.478"}}, {"2014/2015": {"sum": "36.869", "matches": "1", "average": "36.869"}}, {"2013/2014": {"sum": "122.003", "matches": "5", "average": "24.401"}}, {"2010/2011": {"sum": "15.512", "matches": "1", "average": "15.512"}}, {"2009/2010": {"sum": "28.000", "matches": "1", "average": "28.000"}}, {"2008/2009": {"sum": "19.108", "matches": "1", "average": "19.108"}}], "uniao-leiria": [{"2023/2024": {"sum": "20.310", "matches": "1", "average": "20.310"}}], "vitoria-guimaraes": [{"2023/2024": {"sum": "64.944", "matches": "4", "average": "16.236"}}, {"2018/2019": {"sum": "14.543", "matches": "2", "average": "7.272"}}, {"2016/2017": {"sum": "19.643", "matches": "3", "average": "6.548"}}, {"2013/2014": {"sum": "11.500", "matches": "1", "average": "11.500"}}, {"2012/2013": {"sum": "44.720", "matches": "2", "average": "22.360"}}], "cd-tondela": [{"2023/2024": {"sum": "15.721", "matches": "1", "average": "15.721"}}, {"2021/2022": {"sum": "2.862", "matches": "1", "average": "2.862"}}, {"2018/2019": {"sum": "600", "matches": "1", "average": "600"}}, {"2016/2017": {"sum": "800", "matches": "1", "average": "800"}}, {"2013/2014": {"sum": "1.200", "matches": "1", "average": "1.200"}}], "gil-vicente": [{"2023/2024": {"sum": "8.845", "matches": "1", "average": "8.845"}}, {"2015/2016": {"sum": "8.955", "matches": "2", "average": "4.478"}}, {"2014/2015": {"sum": "2.463", "matches": "2", "average": "1.232"}}, {"2013/2014": {"sum": "17.504", "matches": "2", "average": "8.752"}}, {"2012/2013": {"sum": "500", "matches": "1", "average": "500"}}], "fc-penafiel": [{"2023/2024": {"sum": "7.387", "matches": "1", "average": "7.387"}}, {"2018/2019": {"sum": "776", "matches": "1", "average": "776"}}, {"2016/2017": {"sum": "1.425", "matches": "1", "average": "1.425"}}, {"2014/2015": {"sum": "463", "matches": "1", "average": "463"}}, {"2013/2014": {"sum": "6.800", "matches": "2", "average": "3.400"}}, {"2009/2010": {"sum": "14.146", "matches": "1", "average": "14.146"}}], "mortagua-fc": [{"2023/2024": {"sum": "4.381", "matches": "1", "average": "4.381"}}], "cs-maritimo": [{"2023/2024": {"sum": "4.381", "matches": "1", "average": "4.381"}}, {"2018/2019": {"sum": "2.700", "matches": "1", "average": "2.700"}}, {"2014/2015": {"sum": "6.850", "matches": "2", "average": "3.425"}}, {"2013/2014": {"sum": "3.300", "matches": "2", "average": "1.650"}}, {"2011/2012": {"sum": "21.522", "matches": "1", "average": "21.522"}}], "cd-olivais-e-moscavide": [{"2023/2024": {"sum": "4.103", "matches": "1", "average": "4.103"}}], "vilar-de-perdizes": [{"2023/2024": {"sum": "4.036", "matches": "1", "average": "4.036"}}], "fc-vizela": [{"2023/2024": {"sum": "3.798", "matches": "1", "average": "3.798"}}, {"2014/2015": {"sum": "4.000", "matches": "1", "average": "4.000"}}], "vilaverdense-fc": [{"2023/2024": {"sum": "1.500", "matches": "1", "average": "1.500"}}], "sc-farense": [{"2023/2024": {"sum": "1.500", "matches": "1", "average": "1.500"}}, {"2017/2018": {"sum": "10.500", "matches": "1", "average": "10.500"}}], "academico-de-viseu": [{"2022/2023": {"sum": "6.685", "matches": "1", "average": "6.685"}}, {"2019/2020": {"sum": "27.972", "matches": "3", "average": "9.324"}}, {"2013/2014": {"sum": "1.486", "matches": "1", "average": "1.486"}}], "cd-mafra": [{"2021/2022": {"sum": "2.862", "matches": "1", "average": "2.862"}}], "rio-ave-fc": [{"2019/2020": {"sum": "30.000", "matches": "1", "average": "30.000"}}, {"2018/2019": {"sum": "13.608", "matches": "2", "average": "6.804"}}, {"2017/2018": {"sum": "3.200", "matches": "1", "average": "3.200"}}, {"2015/2016": {"sum": "15.537", "matches": "2", "average": "7.769"}}, {"2014/2015": {"sum": "10.242", "matches": "3", "average": "3.414"}}, {"2013/2014": {"sum": "40.250", "matches": "4", "average": "10.063"}}], "varzim-sc": [{"2019/2020": {"sum": "13.179", "matches": "1", "average": "13.179"}}], "cf-canelas-2010": [{"2019/2020": {"sum": "2.000", "matches": "1", "average": "2.000"}}], "pacos-de-ferreira": [{"2019/2020": {"sum": "1.882", "matches": "1", "average": "1.882"}}, {"2018/2019": {"sum": "1.100", "matches": "1", "average": "1.100"}}, {"2016/2017": {"sum": "1.500", "matches": "1", "average": "1.500"}}, {"2014/2015": {"sum": "1.500", "matches": "1", "average": "1.500"}}, {"2013/2014": {"sum": "2.500", "matches": "2", "average": "1.250"}}, {"2012/2013": {"sum": "17.618", "matches": "2", "average": "8.809"}}], "leixoes-sc": [{"2019/2020": {"sum": "890", "matches": "1", "average": "890"}}, {"2018/2019": {"sum": "6.450", "matches": "2", "average": "3.225"}}, {"2016/2017": {"sum": "19.848", "matches": "2", "average": "9.924"}}, {"2013/2014": {"sum": "1.700", "matches": "2", "average": "850"}}], "b-sad": [{"2018/2019": {"sum": "17.717", "matches": "1", "average": "17.717"}}], "fc-arouca": [{"2018/2019": {"sum": "16.454", "matches": "1", "average": "16.454"}}, {"2013/2014": {"sum": "6.500", "matches": "2", "average": "3.250"}}], "sertanense-fc": [{"2018/2019": {"sum": "9.132", "matches": "1", "average": "9.132"}}, {"2013/2014": {"sum": "1.200", "matches": "1", "average": "1.200"}}], "lusitano-fcv": [{"2018/2019": {"sum": "5.820", "matches": "1", "average": "5.820"}}], "cd-feirense": [{"2018/2019": {"sum": "8.061", "matches": "2", "average": "4.031"}}, {"2013/2014": {"sum": "350", "matches": "1", "average": "350"}}], "sc-praiense": [{"2018/2019": {"sum": "3.349", "matches": "1", "average": "3.349"}}], "cdc-montalegre": [{"2018/2019": {"sum": "5.920", "matches": "2", "average": "2.960"}}], "sc-espinho": [{"2018/2019": {"sum": "2.500", "matches": "1", "average": "2.500"}}, {"2014/2015": {"sum": "5.000", "matches": "1", "average": "5.000"}}], "boavista": [{"2018/2019": {"sum": "2.500", "matches": "1", "average": "2.500"}}], "gd-chaves": [{"2018/2019": {"sum": "2.217", "matches": "1", "average": "2.217"}}, {"2016/2017": {"sum": "23.138", "matches": "3", "average": "7.713"}}, {"2014/2015": {"sum": "577", "matches": "1", "average": "577"}}, {"2013/2014": {"sum": "500", "matches": "1", "average": "500"}}, {"2009/2010": {"sum": "28.000", "matches": "1", "average": "28.000"}}], "silves-fc": [{"2018/2019": {"sum": "1.500", "matches": "1", "average": "1.500"}}], "cd-aves": [{"2018/2019": {"sum": "2.768", "matches": "2", "average": "1.384"}}, {"2017/2018": {"sum": "14.866", "matches": "4", "average": "3.717"}}, {"2016/2017": {"sum": "1.500", "matches": "1", "average": "1.500"}}, {"2013/2014": {"sum": "4.400", "matches": "2", "average": "2.200"}}, {"2011/2012": {"sum": "2.310", "matches": "1", "average": "2.310"}}], "casa-pia-ac": [{"2018/2019": {"sum": "1.100", "matches": "1", "average": "1.100"}}], "cd-cova-piedade": [{"2018/2019": {"sum": "823", "matches": "1", "average": "823"}}, {"2017/2018": {"sum": "3.500", "matches": "1", "average": "3.500"}}, {"2013/2014": {"sum": "2.000", "matches": "1", "average": "2.000"}}], "uniao-da-madeira": [{"2018/2019": {"sum": "800", "matches": "1", "average": "800"}}], "vitoria-setubal": [{"2018/2019": {"sum": "776", "matches": "1", "average": "776"}}, {"2016/2017": {"sum": "4.993", "matches": "1", "average": "4.993"}}, {"2013/2014": {"sum": "2.300", "matches": "2", "average": "1.150"}}, {"2010/2011": {"sum": "2.122", "matches": "1", "average": "2.122"}}], "fc-vale-formoso": [{"2018/2019": {"sum": "600", "matches": "1", "average": "600"}}], "sporting-covilha": [{"2018/2019": {"sum": "450", "matches": "1", "average": "450"}}, {"2016/2017": {"sum": "4.827", "matches": "3", "average": "1.609"}}, {"2014/2015": {"sum": "7.000", "matches": "1", "average": "7.000"}}, {"2013/2014": {"sum": "700", "matches": "1", "average": "700"}}], "moreirense-fc": [{"2018/2019": {"sum": "450", "matches": "1", "average": "450"}}, {"2017/2018": {"sum": "4.154", "matches": "1", "average": "4.154"}}, {"2014/2015": {"sum": "22.447", "matches": "1", "average": "22.447"}}], "r-d-agueda": [{"2018/2019": {"sum": "450", "matches": "1", "average": "450"}}], "anadia-fc": [{"2018/2019": {"sum": "350", "matches": "1", "average": "350"}}], "caldas-sc": [{"2017/2018": {"sum": "20.166", "matches": "3", "average": "6.722"}}], "sc-vila-real": [{"2017/2018": {"sum": "2.000", "matches": "1", "average": "2.000"}}], "gd-estoril": [{"2016/2017": {"sum": "34.589", "matches": "4", "average": "8.647"}}, {"2013/2014": {"sum": "14.507", "matches": "3", "average": "4.836"}}], "real-sc": [{"2016/2017": {"sum": "8.000", "matches": "1", "average": "8.000"}}], "gd-gafanha": [{"2016/2017": {"sum": "8.000", "matches": "1", "average": "8.000"}}], "academica-de-coimbra": [{"2016/2017": {"sum": "3.600", "matches": "2", "average": "1.800"}}, {"2013/2014": {"sum": "3.729", "matches": "3", "average": "1.243"}}, {"2011/2012": {"sum": "16.667", "matches": "2", "average": "8.334"}}, {"2010/2011": {"sum": "2.122", "matches": "1", "average": "2.122"}}], "ad-oliveirense": [{"2016/2017": {"sum": "1.500", "matches": "1", "average": "1.500"}}, {"2013/2014": {"sum": "1.500", "matches": "1", "average": "1.500"}}], "ad-sanjoanense": [{"2016/2017": {"sum": "597", "matches": "1", "average": "597"}}], "sc-freamunde": [{"2016/2017": {"sum": "300", "matches": "1", "average": "300"}}, {"2014/2015": {"sum": "708", "matches": "1", "average": "708"}}], "avs": [{"2015/2016": {"sum": "2.832", "matches": "1", "average": "2.832"}}], "cd-nacional": [{"2014/2015": {"sum": "25.030", "matches": "4", "average": "6.258"}}], "os-belenenses": [{"2014/2015": {"sum": "4.404", "matches": "2", "average": "2.202"}}], "oriental-de-lisboa": [{"2014/2015": {"sum": "850", "matches": "1", "average": "850"}}], "santa-maria-fc": [{"2014/2015": {"sum": "215", "matches": "1", "average": "215"}}, {"2013/2014": {"sum": "1.600", "matches": "1", "average": "1.600"}}], "atletico-cp": [{"2013/2014": {"sum": "20.117", "matches": "1", "average": "20.117"}}], "sc-olhanense": [{"2013/2014": {"sum": "2.000", "matches": "1", "average": "2.000"}}, {"2011/2012": {"sum": "600", "matches": "1", "average": "600"}}], "sc-beira-mar": [{"2013/2014": {"sum": "1.393", "matches": "2", "average": "697"}}], "ud-oliveirense": [{"2011/2012": {"sum": "14.957", "matches": "2", "average": "7.479"}}], "cd-pinhalnovense": [{"2010/2011": {"sum": "15.512", "matches": "1", "average": "15.512"}}], "pescadores-caparica": [{"2009/2010": {"sum": "6.000", "matches": "1", "average": "6.000"}}], "estrela-amadora": [{"2008/2009": {"sum": "19.108", "matches": "1", "average": "19.108"}}]}