{"erovnuli-liga": {"dinamo-batumi": [{"icon": "https://tmssl.akamaized.net/images/wappen/tiny/11344.png?lm=1420654425", "season": "2023", "market_value_in_euros": 5560000.0, "country": "Geórgia"}, {"icon": "https://tmssl.akamaized.net/images/wappen/tiny/11344.png?lm=1420654425", "season": "2022", "market_value_in_euros": 16090000.0, "country": "Geórgia"}, {"icon": "https://tmssl.akamaized.net/images/wappen/tiny/11344.png?lm=1420654425", "season": "2021", "market_value_in_euros": 22130000.0, "country": "Geórgia"}, {"icon": "https://tmssl.akamaized.net/images/wappen/tiny/11344.png?lm=1420654425", "season": "2020", "market_value_in_euros": 9700000.0, "country": "Geórgia"}, {"icon": "https://tmssl.akamaized.net/images/wappen/tiny/11344.png?lm=1420654425", "season": "2019", "market_value_in_euros": 5530000.0, "country": "Geórgia"}, {"icon": "https://tmssl.akamaized.net/images/wappen/tiny/11344.png?lm=1420654425", "season": "2018", "market_value_in_euros": 5200000.0, "country": "Geórgia"}], "dinamo-tbilisi": [{"icon": "https://tmssl.akamaized.net/images/wappen/tiny/663.png?lm=1474921564", "season": "2023", "market_value_in_euros": 5450000.0, "country": "Geórgia"}, {"icon": "https://tmssl.akamaized.net/images/wappen/tiny/663.png?lm=1474921564", "season": "2022", "market_value_in_euros": 12640000.0, "country": "Geórgia"}, {"icon": "https://tmssl.akamaized.net/images/wappen/tiny/663.png?lm=1474921564", "season": "2021", "market_value_in_euros": 10700000.0, "country": "Geórgia"}, {"icon": "https://tmssl.akamaized.net/images/wappen/tiny/663.png?lm=1474921564", "season": "2020", "market_value_in_euros": 11830000.0, "country": "Geórgia"}, {"icon": "https://tmssl.akamaized.net/images/wappen/tiny/663.png?lm=1474921564", "season": "2019", "market_value_in_euros": 12600000.0, "country": "Geórgia"}, {"icon": "https://tmssl.akamaized.net/images/wappen/tiny/663.png?lm=1474921564", "season": "2018", "market_value_in_euros": 10130000.0, "country": "Geórgia"}, {"icon": "https://tmssl.akamaized.net/images/wappen/tiny/663.png?lm=1474921564", "season": "2017", "market_value_in_euros": 7600000.0, "country": "Geórgia"}], "torpedo-kutaisi": [{"icon": "https://tmssl.akamaized.net/images/wappen/tiny/253.png?lm=1522184505", "season": "2023", "market_value_in_euros": 5290000.0, "country": "Geórgia"}, {"icon": "https://tmssl.akamaized.net/images/wappen/tiny/253.png?lm=1522184505", "season": "2022", "market_value_in_euros": 7930000.0, "country": "Geórgia"}, {"icon": "https://tmssl.akamaized.net/images/wappen/tiny/253.png?lm=1522184505", "season": "2021", "market_value_in_euros": 7980000.0, "country": "Geórgia"}, {"icon": "https://tmssl.akamaized.net/images/wappen/tiny/253.png?lm=1522184505", "season": "2020", "market_value_in_euros": 7650000.0, "country": "Geórgia"}, {"icon": "https://tmssl.akamaized.net/images/wappen/tiny/253.png?lm=1522184505", "season": "2019", "market_value_in_euros": 8080000.0, "country": "Geórgia"}, {"icon": "https://tmssl.akamaized.net/images/wappen/tiny/253.png?lm=1522184505", "season": "2018", "market_value_in_euros": 8480000.0, "country": "Geórgia"}, {"icon": "https://tmssl.akamaized.net/images/wappen/tiny/253.png?lm=1522184505", "season": "2017", "market_value_in_euros": 8900000.0, "country": "Geórgia"}], "iberia-1999-tbilisi": [{"icon": "https://tmssl.akamaized.net/images/wappen/tiny/41133.png?lm=1614506809", "season": "2023", "market_value_in_euros": 4500000.0, "country": "Geórgia"}], "fc-dila-gori": [{"icon": "https://tmssl.akamaized.net/images/wappen/tiny/32017.png?lm=1635148161", "season": "2023", "market_value_in_euros": 4099999.9999999995, "country": "Geórgia"}, {"icon": "https://tmssl.akamaized.net/images/wappen/tiny/32017.png?lm=1635148161", "season": "2022", "market_value_in_euros": 6030000.0, "country": "Geórgia"}, {"icon": "https://tmssl.akamaized.net/images/wappen/tiny/32017.png?lm=1635148161", "season": "2021", "market_value_in_euros": 5950000.0, "country": "Geórgia"}, {"icon": "https://tmssl.akamaized.net/images/wappen/tiny/32017.png?lm=1635148161", "season": "2020", "market_value_in_euros": 5600000.0, "country": "Geórgia"}, {"icon": "https://tmssl.akamaized.net/images/wappen/tiny/32017.png?lm=1635148161", "season": "2019", "market_value_in_euros": 4430000.0, "country": "Geórgia"}, {"icon": "https://tmssl.akamaized.net/images/wappen/tiny/32017.png?lm=1635148161", "season": "2018", "market_value_in_euros": 4650000.0, "country": "Geórgia"}, {"icon": "https://tmssl.akamaized.net/images/wappen/tiny/32017.png?lm=1635148161", "season": "2017", "market_value_in_euros": 3300000.0, "country": "Geórgia"}], "fc-kolkheti-1913-poti": [{"icon": "https://tmssl.akamaized.net/images/wappen/tiny/28971.png?lm=1420654467", "season": "2023", "market_value_in_euros": 3230000.0, "country": "Geórgia"}], "fc-telavi": [{"icon": "https://tmssl.akamaized.net/images/wappen/tiny/41310.png?lm=1554148788", "season": "2023", "market_value_in_euros": 3000000.0, "country": "Geórgia"}, {"icon": "https://tmssl.akamaized.net/images/wappen/tiny/41310.png?lm=1554148788", "season": "2022", "market_value_in_euros": 8130000.000000001, "country": "Geórgia"}, {"icon": "https://tmssl.akamaized.net/images/wappen/tiny/41310.png?lm=1554148788", "season": "2021", "market_value_in_euros": 5080000.0, "country": "Geórgia"}, {"icon": "https://tmssl.akamaized.net/images/wappen/tiny/41310.png?lm=1554148788", "season": "2020", "market_value_in_euros": 4080000.0, "country": "Geórgia"}, {"icon": "https://tmssl.akamaized.net/images/wappen/tiny/41310.png?lm=1554148788", "season": "2019", "market_value_in_euros": 1800000.0, "country": "Geórgia"}], "fc-samgurali-tskaltubo": [{"icon": "https://tmssl.akamaized.net/images/wappen/tiny/29675.png?lm=1579789783", "season": "2023", "market_value_in_euros": 2930000.0, "country": "Geórgia"}, {"icon": "https://tmssl.akamaized.net/images/wappen/tiny/29675.png?lm=1579789783", "season": "2022", "market_value_in_euros": 4740000.0, "country": "Geórgia"}, {"icon": "https://tmssl.akamaized.net/images/wappen/tiny/29675.png?lm=1579789783", "season": "2021", "market_value_in_euros": 3600000.0, "country": "Geórgia"}, {"icon": "https://tmssl.akamaized.net/images/wappen/tiny/29675.png?lm=1579789783", "season": "2020", "market_value_in_euros": 2580000.0, "country": "Geórgia"}], "fc-gagra": [{"icon": "https://tmssl.akamaized.net/images/wappen/tiny/22842.png?lm=1553020103", "season": "2023", "market_value_in_euros": 2450000.0, "country": "Geórgia"}, {"icon": "https://tmssl.akamaized.net/images/wappen/tiny/22842.png?lm=1553020103", "season": "2022", "market_value_in_euros": 5100000.0, "country": "Geórgia"}, {"icon": "https://tmssl.akamaized.net/images/wappen/tiny/22842.png?lm=1553020103", "season": "2021", "market_value_in_euros": 6200000.0, "country": "Geórgia"}], "fc-samtredia": [{"icon": "https://tmssl.akamaized.net/images/wappen/tiny/2950.png?lm=1678977755", "season": "2023", "market_value_in_euros": 2400000.0, "country": "Geórgia"}, {"icon": "https://tmssl.akamaized.net/images/wappen/tiny/2950.png?lm=1678977755", "season": "2022", "market_value_in_euros": 3320000.0, "country": "Geórgia"}, {"icon": "https://tmssl.akamaized.net/images/wappen/tiny/2950_1678977728.png?lm=1678977728", "season": "2020", "market_value_in_euros": 6330000.0, "country": "Geórgia"}, {"icon": "https://tmssl.akamaized.net/images/wappen/tiny/2950_1678977728.png?lm=1678977728", "season": "2019", "market_value_in_euros": 5630000.0, "country": "Geórgia"}, {"icon": "https://tmssl.akamaized.net/images/wappen/tiny/2950_1678977728.png?lm=1678977728", "season": "2017", "market_value_in_euros": 10430000.0, "country": "Geórgia"}], "fc-saburtalo": [{"icon": "https://tmssl.akamaized.net/images/wappen/tiny/41133_1709487069.png?lm=1709487069", "season": "2022", "market_value_in_euros": 6740000.0, "country": "Geórgia"}, {"icon": "https://tmssl.akamaized.net/images/wappen/tiny/41133_1614506844.png?lm=1614506845", "season": "2021", "market_value_in_euros": 6650000.0, "country": "Geórgia"}, {"icon": "https://tmssl.akamaized.net/images/wappen/tiny/41133_1614506844.png?lm=1614506845", "season": "2020", "market_value_in_euros": 5880000.0, "country": "Geórgia"}, {"icon": "https://tmssl.akamaized.net/images/wappen/tiny/41133_1614506844.png?lm=1614506845", "season": "2019", "market_value_in_euros": 7050000.0, "country": "Geórgia"}, {"icon": "https://tmssl.akamaized.net/images/wappen/tiny/41133_1614506844.png?lm=1614506845", "season": "2018", "market_value_in_euros": 5780000.0, "country": "Geórgia"}, {"icon": "https://tmssl.akamaized.net/images/wappen/tiny/41133_1614506844.png?lm=1614506845", "season": "2017", "market_value_in_euros": 5980000.0, "country": "Geórgia"}], "shukura-kobuleti": [{"icon": "https://tmssl.akamaized.net/images/wappen/tiny/37760.png?lm=1614506993", "season": "2022", "market_value_in_euros": 3310000.0, "country": "Geórgia"}, {"icon": "https://tmssl.akamaized.net/images/wappen/tiny/37760.png?lm=1614506993", "season": "2020", "market_value_in_euros": 2780000.0, "country": "Geórgia"}], "fc-locomotive-tbilisi": [{"icon": "https://tmssl.akamaized.net/images/wappen/tiny/6365.png?lm=1522184600", "season": "2021", "market_value_in_euros": 5200000.0, "country": "Geórgia"}, {"icon": "https://tmssl.akamaized.net/images/wappen/tiny/6365.png?lm=1522184600", "season": "2020", "market_value_in_euros": 4780000.0, "country": "Geórgia"}, {"icon": "https://tmssl.akamaized.net/images/wappen/tiny/6365.png?lm=1522184600", "season": "2019", "market_value_in_euros": 4200000.0, "country": "Geórgia"}, {"icon": "https://tmssl.akamaized.net/images/wappen/tiny/6365.png?lm=1522184600", "season": "2018", "market_value_in_euros": 4880000.0, "country": "Geórgia"}, {"icon": "https://tmssl.akamaized.net/images/wappen/tiny/6365.png?lm=1522184600", "season": "2017", "market_value_in_euros": 4250000.0, "country": "Geórgia"}], "sioni-bolnisi": [{"icon": "https://tmssl.akamaized.net/images/wappen/tiny/10531.png?lm=1420654358", "season": "2021", "market_value_in_euros": 3830000.0, "country": "Geórgia"}, {"icon": "https://tmssl.akamaized.net/images/wappen/tiny/10531.png?lm=1420654358", "season": "2018", "market_value_in_euros": 3550000.0, "country": "Geórgia"}, {"icon": "https://tmssl.akamaized.net/images/wappen/tiny/10531.png?lm=1420654358", "season": "2017", "market_value_in_euros": 3100000.0, "country": "Geórgia"}], "chikhura-sachkhere": [{"icon": "https://tmssl.akamaized.net/images/wappen/tiny/11435.png?lm=1409253000", "season": "2019", "market_value_in_euros": 4630000.0, "country": "Geórgia"}, {"icon": "https://tmssl.akamaized.net/images/wappen/tiny/11435.png?lm=1409253000", "season": "2018", "market_value_in_euros": 3830000.0, "country": "Geórgia"}, {"icon": "https://tmssl.akamaized.net/images/wappen/tiny/11435.png?lm=1409253000", "season": "2017", "market_value_in_euros": 5250000.0, "country": "Geórgia"}], "merani-tbilisi": [{"icon": "https://tmssl.akamaized.net/images/wappen/tiny/32770.png?lm=1568575697", "season": "2019", "market_value_in_euros": 2130000.0, "country": "Geórgia"}], "fc-rustavi": [{"icon": "https://tmssl.akamaized.net/images/wappen/tiny/1799.png?lm=1552479737", "season": "2018", "market_value_in_euros": 5230000.0, "country": "Geórgia"}, {"icon": "https://tmssl.akamaized.net/images/wappen/tiny/1799.png?lm=1552479737", "season": "2017", "market_value_in_euros": 9250000.0, "country": "Geórgia"}], "wit-georgia-tbilisi": [{"icon": "https://tmssl.akamaized.net/images/wappen/tiny/751_1650957761.png?lm=1650957761", "season": "2018", "market_value_in_euros": 2049999.9999999998, "country": "Geórgia"}], "kolkheti-1913-poti": [{"icon": "https://tmssl.akamaized.net/images/wappen/tiny/28971_1702653432.png?lm=1702653432", "season": "2017", "market_value_in_euros": 4500000.0, "country": "Geórgia"}]}}{"erovnuli-liga": {"dinamo-batumi": [{"icon": "https://tmssl.akamaized.net/images/wappen/tiny/11344.png?lm=1420654425", "season": "2023", "market_value_in_euros": 5560000.0, "country": "Ge\u00f3rgia"}, {"icon": "https://tmssl.akamaized.net/images/wappen/tiny/11344.png?lm=1420654425", "season": "2022", "market_value_in_euros": 16090000.0, "country": "Ge\u00f3rgia"}, {"icon": "https://tmssl.akamaized.net/images/wappen/tiny/11344.png?lm=1420654425", "season": "2021", "market_value_in_euros": 22130000.0, "country": "Ge\u00f3rgia"}, {"icon": "https://tmssl.akamaized.net/images/wappen/tiny/11344.png?lm=1420654425", "season": "2020", "market_value_in_euros": 9700000.0, "country": "Ge\u00f3rgia"}, {"icon": "https://tmssl.akamaized.net/images/wappen/tiny/11344.png?lm=1420654425", "season": "2019", "market_value_in_euros": 5530000.0, "country": "Ge\u00f3rgia"}, {"icon": "https://tmssl.akamaized.net/images/wappen/tiny/11344.png?lm=1420654425", "season": "2018", "market_value_in_euros": 5200000.0, "country": "Ge\u00f3rgia"}], "dinamo-tbilisi": [{"icon": "https://tmssl.akamaized.net/images/wappen/tiny/663.png?lm=1474921564", "season": "2023", "market_value_in_euros": 5450000.0, "country": "Ge\u00f3rgia"}, {"icon": "https://tmssl.akamaized.net/images/wappen/tiny/663.png?lm=1474921564", "season": "2022", "market_value_in_euros": 12640000.0, "country": "Ge\u00f3rgia"}, {"icon": "https://tmssl.akamaized.net/images/wappen/tiny/663.png?lm=1474921564", "season": "2021", "market_value_in_euros": 10700000.0, "country": "Ge\u00f3rgia"}, {"icon": "https://tmssl.akamaized.net/images/wappen/tiny/663.png?lm=1474921564", "season": "2020", "market_value_in_euros": 11830000.0, "country": "Ge\u00f3rgia"}, {"icon": "https://tmssl.akamaized.net/images/wappen/tiny/663.png?lm=1474921564", "season": "2019", "market_value_in_euros": 12600000.0, "country": "Ge\u00f3rgia"}, {"icon": "https://tmssl.akamaized.net/images/wappen/tiny/663.png?lm=1474921564", "season": "2018", "market_value_in_euros": 10130000.0, "country": "Ge\u00f3rgia"}, {"icon": "https://tmssl.akamaized.net/images/wappen/tiny/663.png?lm=1474921564", "season": "2017", "market_value_in_euros": 7600000.0, "country": "Ge\u00f3rgia"}], "torpedo-kutaisi": [{"icon": "https://tmssl.akamaized.net/images/wappen/tiny/253.png?lm=1522184505", "season": "2023", "market_value_in_euros": 5290000.0, "country": "Ge\u00f3rgia"}, {"icon": "https://tmssl.akamaized.net/images/wappen/tiny/253.png?lm=1522184505", "season": "2022", "market_value_in_euros": 7930000.0, "country": "Ge\u00f3rgia"}, {"icon": "https://tmssl.akamaized.net/images/wappen/tiny/253.png?lm=1522184505", "season": "2021", "market_value_in_euros": 7980000.0, "country": "Ge\u00f3rgia"}, {"icon": "https://tmssl.akamaized.net/images/wappen/tiny/253.png?lm=1522184505", "season": "2020", "market_value_in_euros": 7650000.0, "country": "Ge\u00f3rgia"}, {"icon": "https://tmssl.akamaized.net/images/wappen/tiny/253.png?lm=1522184505", "season": "2019", "market_value_in_euros": 8080000.0, "country": "Ge\u00f3rgia"}, {"icon": "https://tmssl.akamaized.net/images/wappen/tiny/253.png?lm=1522184505", "season": "2018", "market_value_in_euros": 8480000.0, "country": "Ge\u00f3rgia"}, {"icon": "https://tmssl.akamaized.net/images/wappen/tiny/253.png?lm=1522184505", "season": "2017", "market_value_in_euros": 8900000.0, "country": "Ge\u00f3rgia"}], "iberia-1999-tbilisi": [{"icon": "https://tmssl.akamaized.net/images/wappen/tiny/41133.png?lm=1614506809", "season": "2023", "market_value_in_euros": 4500000.0, "country": "Ge\u00f3rgia"}], "fc-dila-gori": [{"icon": "https://tmssl.akamaized.net/images/wappen/tiny/32017.png?lm=1635148161", "season": "2023", "market_value_in_euros": 4099999.9999999995, "country": "Ge\u00f3rgia"}, {"icon": "https://tmssl.akamaized.net/images/wappen/tiny/32017.png?lm=1635148161", "season": "2022", "market_value_in_euros": 6030000.0, "country": "Ge\u00f3rgia"}, {"icon": "https://tmssl.akamaized.net/images/wappen/tiny/32017.png?lm=1635148161", "season": "2021", "market_value_in_euros": 5950000.0, "country": "Ge\u00f3rgia"}, {"icon": "https://tmssl.akamaized.net/images/wappen/tiny/32017.png?lm=1635148161", "season": "2020", "market_value_in_euros": 5600000.0, "country": "Ge\u00f3rgia"}, {"icon": "https://tmssl.akamaized.net/images/wappen/tiny/32017.png?lm=1635148161", "season": "2019", "market_value_in_euros": 4430000.0, "country": "Ge\u00f3rgia"}, {"icon": "https://tmssl.akamaized.net/images/wappen/tiny/32017.png?lm=1635148161", "season": "2018", "market_value_in_euros": 4650000.0, "country": "Ge\u00f3rgia"}, {"icon": "https://tmssl.akamaized.net/images/wappen/tiny/32017.png?lm=1635148161", "season": "2017", "market_value_in_euros": 3300000.0, "country": "Ge\u00f3rgia"}], "fc-kolkheti-1913-poti": [{"icon": "https://tmssl.akamaized.net/images/wappen/tiny/28971.png?lm=1420654467", "season": "2023", "market_value_in_euros": 3230000.0, "country": "Ge\u00f3rgia"}], "fc-telavi": [{"icon": "https://tmssl.akamaized.net/images/wappen/tiny/41310.png?lm=1554148788", "season": "2023", "market_value_in_euros": 3000000.0, "country": "Ge\u00f3rgia"}, {"icon": "https://tmssl.akamaized.net/images/wappen/tiny/41310.png?lm=1554148788", "season": "2022", "market_value_in_euros": 8130000.000000001, "country": "Ge\u00f3rgia"}, {"icon": "https://tmssl.akamaized.net/images/wappen/tiny/41310.png?lm=1554148788", "season": "2021", "market_value_in_euros": 5080000.0, "country": "Ge\u00f3rgia"}, {"icon": "https://tmssl.akamaized.net/images/wappen/tiny/41310.png?lm=1554148788", "season": "2020", "market_value_in_euros": 4080000.0, "country": "Ge\u00f3rgia"}, {"icon": "https://tmssl.akamaized.net/images/wappen/tiny/41310.png?lm=1554148788", "season": "2019", "market_value_in_euros": 1800000.0, "country": "Ge\u00f3rgia"}], "fc-samgurali-tskaltubo": [{"icon": "https://tmssl.akamaized.net/images/wappen/tiny/29675.png?lm=1579789783", "season": "2023", "market_value_in_euros": 2930000.0, "country": "Ge\u00f3rgia"}, {"icon": "https://tmssl.akamaized.net/images/wappen/tiny/29675.png?lm=1579789783", "season": "2022", "market_value_in_euros": 4740000.0, "country": "Ge\u00f3rgia"}, {"icon": "https://tmssl.akamaized.net/images/wappen/tiny/29675.png?lm=1579789783", "season": "2021", "market_value_in_euros": 3600000.0, "country": "Ge\u00f3rgia"}, {"icon": "https://tmssl.akamaized.net/images/wappen/tiny/29675.png?lm=1579789783", "season": "2020", "market_value_in_euros": 2580000.0, "country": "Ge\u00f3rgia"}], "fc-gagra": [{"icon": "https://tmssl.akamaized.net/images/wappen/tiny/22842.png?lm=1553020103", "season": "2023", "market_value_in_euros": 2450000.0, "country": "Ge\u00f3rgia"}, {"icon": "https://tmssl.akamaized.net/images/wappen/tiny/22842.png?lm=1553020103", "season": "2022", "market_value_in_euros": 5100000.0, "country": "Ge\u00f3rgia"}, {"icon": "https://tmssl.akamaized.net/images/wappen/tiny/22842.png?lm=1553020103", "season": "2021", "market_value_in_euros": 6200000.0, "country": "Ge\u00f3rgia"}], "fc-samtredia": [{"icon": "https://tmssl.akamaized.net/images/wappen/tiny/2950.png?lm=1678977755", "season": "2023", "market_value_in_euros": 2400000.0, "country": "Ge\u00f3rgia"}, {"icon": "https://tmssl.akamaized.net/images/wappen/tiny/2950.png?lm=1678977755", "season": "2022", "market_value_in_euros": 3320000.0, "country": "Ge\u00f3rgia"}, {"icon": "https://tmssl.akamaized.net/images/wappen/tiny/2950_1678977728.png?lm=1678977728", "season": "2020", "market_value_in_euros": 6330000.0, "country": "Ge\u00f3rgia"}, {"icon": "https://tmssl.akamaized.net/images/wappen/tiny/2950_1678977728.png?lm=1678977728", "season": "2019", "market_value_in_euros": 5630000.0, "country": "Ge\u00f3rgia"}, {"icon": "https://tmssl.akamaized.net/images/wappen/tiny/2950_1678977728.png?lm=1678977728", "season": "2017", "market_value_in_euros": 10430000.0, "country": "Ge\u00f3rgia"}], "fc-saburtalo": [{"icon": "https://tmssl.akamaized.net/images/wappen/tiny/41133_1709487069.png?lm=1709487069", "season": "2022", "market_value_in_euros": 6740000.0, "country": "Ge\u00f3rgia"}, {"icon": "https://tmssl.akamaized.net/images/wappen/tiny/41133_1614506844.png?lm=1614506845", "season": "2021", "market_value_in_euros": 6650000.0, "country": "Ge\u00f3rgia"}, {"icon": "https://tmssl.akamaized.net/images/wappen/tiny/41133_1614506844.png?lm=1614506845", "season": "2020", "market_value_in_euros": 5880000.0, "country": "Ge\u00f3rgia"}, {"icon": "https://tmssl.akamaized.net/images/wappen/tiny/41133_1614506844.png?lm=1614506845", "season": "2019", "market_value_in_euros": 7050000.0, "country": "Ge\u00f3rgia"}, {"icon": "https://tmssl.akamaized.net/images/wappen/tiny/41133_1614506844.png?lm=1614506845", "season": "2018", "market_value_in_euros": 5780000.0, "country": "Ge\u00f3rgia"}, {"icon": "https://tmssl.akamaized.net/images/wappen/tiny/41133_1614506844.png?lm=1614506845", "season": "2017", "market_value_in_euros": 5980000.0, "country": "Ge\u00f3rgia"}], "shukura-kobuleti": [{"icon": "https://tmssl.akamaized.net/images/wappen/tiny/37760.png?lm=1614506993", "season": "2022", "market_value_in_euros": 3310000.0, "country": "Ge\u00f3rgia"}, {"icon": "https://tmssl.akamaized.net/images/wappen/tiny/37760.png?lm=1614506993", "season": "2020", "market_value_in_euros": 2780000.0, "country": "Ge\u00f3rgia"}], "fc-locomotive-tbilisi": [{"icon": "https://tmssl.akamaized.net/images/wappen/tiny/6365.png?lm=1522184600", "season": "2021", "market_value_in_euros": 5200000.0, "country": "Ge\u00f3rgia"}, {"icon": "https://tmssl.akamaized.net/images/wappen/tiny/6365.png?lm=1522184600", "season": "2020", "market_value_in_euros": 4780000.0, "country": "Ge\u00f3rgia"}, {"icon": "https://tmssl.akamaized.net/images/wappen/tiny/6365.png?lm=1522184600", "season": "2019", "market_value_in_euros": 4200000.0, "country": "Ge\u00f3rgia"}, {"icon": "https://tmssl.akamaized.net/images/wappen/tiny/6365.png?lm=1522184600", "season": "2018", "market_value_in_euros": 4880000.0, "country": "Ge\u00f3rgia"}, {"icon": "https://tmssl.akamaized.net/images/wappen/tiny/6365.png?lm=1522184600", "season": "2017", "market_value_in_euros": 4250000.0, "country": "Ge\u00f3rgia"}], "sioni-bolnisi": [{"icon": "https://tmssl.akamaized.net/images/wappen/tiny/10531.png?lm=1420654358", "season": "2021", "market_value_in_euros": 3830000.0, "country": "Ge\u00f3rgia"}, {"icon": "https://tmssl.akamaized.net/images/wappen/tiny/10531.png?lm=1420654358", "season": "2018", "market_value_in_euros": 3550000.0, "country": "Ge\u00f3rgia"}, {"icon": "https://tmssl.akamaized.net/images/wappen/tiny/10531.png?lm=1420654358", "season": "2017", "market_value_in_euros": 3100000.0, "country": "Ge\u00f3rgia"}], "chikhura-sachkhere": [{"icon": "https://tmssl.akamaized.net/images/wappen/tiny/11435.png?lm=1409253000", "season": "2019", "market_value_in_euros": 4630000.0, "country": "Ge\u00f3rgia"}, {"icon": "https://tmssl.akamaized.net/images/wappen/tiny/11435.png?lm=1409253000", "season": "2018", "market_value_in_euros": 3830000.0, "country": "Ge\u00f3rgia"}, {"icon": "https://tmssl.akamaized.net/images/wappen/tiny/11435.png?lm=1409253000", "season": "2017", "market_value_in_euros": 5250000.0, "country": "Ge\u00f3rgia"}], "merani-tbilisi": [{"icon": "https://tmssl.akamaized.net/images/wappen/tiny/32770.png?lm=1568575697", "season": "2019", "market_value_in_euros": 2130000.0, "country": "Ge\u00f3rgia"}], "fc-rustavi": [{"icon": "https://tmssl.akamaized.net/images/wappen/tiny/1799.png?lm=1552479737", "season": "2018", "market_value_in_euros": 5230000.0, "country": "Ge\u00f3rgia"}, {"icon": "https://tmssl.akamaized.net/images/wappen/tiny/1799.png?lm=1552479737", "season": "2017", "market_value_in_euros": 9250000.0, "country": "Ge\u00f3rgia"}], "wit-georgia-tbilisi": [{"icon": "https://tmssl.akamaized.net/images/wappen/tiny/751_1650957761.png?lm=1650957761", "season": "2018", "market_value_in_euros": 2049999.9999999998, "country": "Ge\u00f3rgia"}], "kolkheti-1913-poti": [{"icon": "https://tmssl.akamaized.net/images/wappen/tiny/28971_1702653432.png?lm=1702653432", "season": "2017", "market_value_in_euros": 4500000.0, "country": "Ge\u00f3rgia"}]}}